.gitignore
.travis.yml
CHANGELOG.rst
LICENSE-MIT
MANIFEST.in
README.rst
requirements-dev.txt
requirements.txt
setup.py
test.sh
httpretty_fixtures/__init__.py
httpretty_fixtures.egg-info/PKG-INFO
httpretty_fixtures.egg-info/SOURCES.txt
httpretty_fixtures.egg-info/dependency_links.txt
httpretty_fixtures.egg-info/requires.txt
httpretty_fixtures.egg-info/top_level.txt
httpretty_fixtures/test/__init__.py
httpretty_fixtures/test/test.py