Metadata-Version: 1.1
Name: httpretty-fixtures
Version: 2.1.1
Summary: Fixture manager for httpretty
Home-page: https://github.com/underdogio/httpretty-fixtures
Author: Todd Wolfson
Author-email: todd@twolfson.com
License: MIT
Download-URL: https://github.com/underdogio/httpretty-fixtures/archive/master.zip
Keywords: httpretty,fixture,responses,mock
Platform: UNKNOWN
Classifier: Development Status :: 3 - Alpha
Classifier: Intended Audience :: Developers
Classifier: License :: Public Domain
Classifier: Operating System :: OS Independent
Classifier: Programming Language :: Python :: 2
Classifier: Programming Language :: Python :: 2.7
Classifier: Programming Language :: Python :: 3
Classifier: Programming Language :: Python :: 3.3
Classifier: Programming Language :: Python :: 3.4
Classifier: Programming Language :: Python :: 3.5
Classifier: Programming Language :: Python
